[
  {
    "path": "/",
    "page": "./home",
    "chunk": "main",
    "data": {
      "articles": "GET https://gist.githubusercontent.com/koistya/a32919e847531320675764e7308b796a/raw/articles.json"
    }
  },
  {
    "path": "/error",
    "page": "./error",
    "chunk": "main"
  },
  {
    "path": "/about",
    "page": "./about"
  },
  {
    "path": "/tasks/:status(pending|completed)?",
    "page": "./home"
  },
  {
    "path": "/login",
    "page": "./login"
  },
  {
    "path": "/signup",
    "page": "./signup"
  },
  {
    "path": "/syllabus",
    "page": "./syllabus",
    "data": {
      "subjects": "GET http://localhost:4000/api/Syllabuses/58d65f3b120b8d4fd343a821/subjects"
    }
  },
  {
    "path": "/feed",
    "page": "./feed",
    "data": {
      "articles": "GET http://localhost:4000/api/Articles"
    }
  },
  {
    "path": "/timeline",
    "page": "./timeline",
    "data": {
      "breaks": "GET http://localhost:4000/api/Timelines/58d68371120b8d4fd343a829/breaks",
      "sessions": "GET http://localhost:4000/api/Timelines/58d68371120b8d4fd343a829/sessions"
    }
  },
  {
    "path": "/calendar",
    "page": "./calendar"
  },
  {
    "path": "/settings",
    "page": "./settings"
  },
  {
    "path": "/profile",
    "page": "./profile"
  },
  {
    "path": "/editor",
    "page": "./editor"
  },
  {
    "path": "/timer/:timerid",
    "page": "./timer"
  }
]
